{

  "devices":{
    "of:0000000000000021":{ "basic":{ "name":"SS1", "latitude":40, "longitude":-100 } },
    "of:0000000000000022":{ "basic":{ "name":"SS2", "latitude":40, "longitude":-90  } },
    "of:0000000000000011":{ "basic":{ "name":"LS1", "latitude":35, "longitude":-100 } },
    "of:0000000000000012":{ "basic":{ "name":"LS2", "latitude":35, "longitude":-90  } }
  },

  "ports" : {
    "of:0000000000000021/31" : { "interfaces" : [ { "name" : "SS1_LS1" } ] },
    "of:0000000000000021/32" : { "interfaces" : [ { "name" : "SS1_LS2" } ] },

    "of:0000000000000022/31" : { "interfaces" : [ { "name" : "SS2_LS1" } ] },
    "of:0000000000000022/32" : { "interfaces" : [ { "name" : "SS2_LS2" } ] },

    "of:0000000000000011/1" : { "interfaces" : [ { "name" : "mst-001" } ] },
    "of:0000000000000011/2" : { "interfaces" : [ { "name" : "ant-001" } ] },
    "of:0000000000000011/3" : { "interfaces" : [ { "name" : "ant-002" } ] },
    "of:0000000000000011/4" : { "interfaces" : [ { "name" : "dgx-1" } ] },
    "of:0000000000000011/5" : { "interfaces" : [ { "name" : "mst-002" } ] },
    "of:0000000000000011/51" : { "interfaces" : [ { "name" : "ssd-1-1" } ] },
    "of:0000000000000011/52" : { "interfaces" : [ { "name" : "ssd-1-2" } ] },

    "of:0000000000000011/53" : { "interfaces" : [ { "name" : "LS1_SS1" } ] },
    "of:0000000000000011/54" : { "interfaces" : [ { "name" : "LS1_SS2" } ] },

    "of:0000000000000012/1" : { "interfaces" : [ { "name" : "ant-003" } ] },
    "of:0000000000000012/2" : { "interfaces" : [ { "name" : "ant-004" } ] },
    "of:0000000000000012/3" : { "interfaces" : [ { "name" : "ant-005" } ] },
    "of:0000000000000012/4" : { "interfaces" : [ { "name" : "ant-006" } ] },
    "of:0000000000000012/1001" : { "interfaces" : [ { "name" : "ant-007" } ] },
    "of:0000000000000012/1002" : { "interfaces" : [ { "name" : "ant-008" } ] },
    "of:0000000000000012/51" : { "interfaces" : [ { "name" : "ssd-1-3" } ] },
    "of:0000000000000012/52" : { "interfaces" : [ { "name" : "ssd-1-4" } ] },

    "of:0000000000000012/53" : { "interfaces" : [ { "name" : "LS2_SS1" } ] },
    "of:0000000000000012/54" : { "interfaces" : [ { "name" : "LS2_SS2" } ] }
  },

  "apps" : {
    "org.onosproject.simplefabric" : {
      "simpleFabric" : {
        "l2Networks" : [
          { "name" : "LEAF1", "interfaces" : ["mst-001", "ant-001", "ant-002", "dgx-1", "mst-002", "ssd-1-1", "ssd-1-2"], "l2Forward" : true, "l2Broadcast" : false },
          { "name" : "LEAF2", "interfaces" : ["ant-003", "ant-004", "ant-005", "ant-006", "ant-007", "ant-008", "ssd-1-3", "ssd-1-4"], "l2Forward" : true, "l2Broadcast" : false }
        ],
        "ipSubnets" : [
           { "ipPrefix" : "192.168.110.0/24", "gatewayIp" : "192.168.110.1", "gatewayMac" : "00:00:c0:a8:6e:01", "l2NetworkName" : "LEAF1" },
           { "ipPrefix" : "192.168.111.0/24", "gatewayIp" : "192.168.111.1", "gatewayMac" : "00:00:c0:a8:6f:01", "l2NetworkName" : "LEAF2" }
        ],
        "borderRoutes" : [
           { "ipPrefix" : "192.168.200.0/24", "nextHop" : "192.168.110.2" }
        ]
      }
    }
  }

}

